msensor/__init__.py
msensor/example_main.py
msensor/make_proto.py
msensor/sim_adapter.py
msensor/protobuf/__init__.py
msensor/protobuf/morai_actor_pb2.py
msensor/protobuf/morai_actor_pb2_grpc.py
msensor/protobuf/morai_mgeo_pb2.py
msensor/protobuf/morai_mgeo_pb2_grpc.py
msensor/protobuf/morai_sensor_pb2.py
msensor/protobuf/morai_sensor_pb2_grpc.py
msensor/protobuf/morai_sim_info_pb2.py
msensor/protobuf/morai_sim_info_pb2_grpc.py
msensor/protobuf/morai_simulation_pb2.py
msensor/protobuf/morai_simulation_pb2_grpc.py
msensor/protobuf/morai_type_pb2.py
msensor/protobuf/morai_type_pb2_grpc.py
morai_api-0.0.2.dist-info/LICENSE.txt
morai_api-0.0.2.dist-info/METADATA
morai_api-0.0.2.dist-info/WHEEL
morai_api-0.0.2.dist-info/top_level.txt
morai_api-0.0.2.dist-info/RECORD
