Metadata-Version: 2.1
Name: morai-api
Version: 0.0.2
Summary: MORAI Sensor API
Author: ischoi
Author-email: ischoi@morai.ai
Classifier: Programming Language :: Python :: 3
Classifier: License :: OSI Approved :: MIT License
Classifier: Operating System :: OS Independent
Requires-Python: >=3.6
License-File: LICENSE.txt
